mongo2arango/__init__.py
mongo2arango/config.py
mongo2arango/dryRun.py
mongo2arango/initIntegrate.py
mongo2arango/models.py
mongo2arango/mongo2arango_cli.py
mongo2arango-0.2.2.dist-info/METADATA
mongo2arango-0.2.2.dist-info/WHEEL
mongo2arango-0.2.2.dist-info/entry_points.txt
mongo2arango-0.2.2.dist-info/RECORD
