Metadata-Version: 2.1
Name: mongo2arango
Version: 0.2.2
Summary: A tool to migrate data from MongoDB to ArangoDB.
License: MIT
Keywords: mongodb,arangodb,migration
Author: tadeasf
Author-email: taddy.fort@gmail.com
Requires-Python: >=3.9,<4.0
Classifier: License :: OSI Approved :: MIT License
Classifier: Operating System :: OS Independent
Classifier: Programming Language :: Python :: 3
Classifier: Programming Language :: Python :: 3.9
Classifier: Programming Language :: Python :: 3.10
Classifier: Programming Language :: Python :: 3.11
Requires-Dist: arango-orm (>=0.7.2,<0.8.0)
Requires-Dist: click (>=8.1.6,<9.0.0)
Requires-Dist: ijson (>=3.2.3,<4.0.0)
Requires-Dist: pymongo (>=4.4.1,<5.0.0)
Requires-Dist: python-arango (==7.1.0)
Requires-Dist: python-dotenv (>=1.0.0,<2.0.0)
Requires-Dist: simplejson (>=3.19.1,<4.0.0)
Requires-Dist: six (>=1.16.0,<2.0.0)
Requires-Dist: tqdm (>=4.66.1,<5.0.0)
